LICENSE
MANIFEST.in
Makefile
README.md
SHORT_README.md
setup.py
lib/hnswlib/.git
lib/hnswlib/.gitignore
lib/hnswlib/ALGO_PARAMS.md
lib/hnswlib/CMakeLists.txt
lib/hnswlib/LICENSE
lib/hnswlib/MANIFEST.in
lib/hnswlib/Makefile
lib/hnswlib/README.md
lib/hnswlib/TESTING_RECALL.md
lib/hnswlib/pyproject.toml
lib/hnswlib/setup.py
lib/hnswlib/.github/workflows/build.yml
lib/hnswlib/examples/cpp/EXAMPLES.md
lib/hnswlib/examples/cpp/example_filter.cpp
lib/hnswlib/examples/cpp/example_mt_filter.cpp
lib/hnswlib/examples/cpp/example_mt_replace_deleted.cpp
lib/hnswlib/examples/cpp/example_mt_search.cpp
lib/hnswlib/examples/cpp/example_replace_deleted.cpp
lib/hnswlib/examples/cpp/example_search.cpp
lib/hnswlib/examples/python/EXAMPLES.md
lib/hnswlib/examples/python/example.py
lib/hnswlib/examples/python/example_filter.py
lib/hnswlib/examples/python/example_replace_deleted.py
lib/hnswlib/examples/python/example_search.py
lib/hnswlib/examples/python/example_serialization.py
lib/hnswlib/examples/python/pyw_hnswlib.py
lib/hnswlib/hnswlib/bruteforce.h
lib/hnswlib/hnswlib/hnswalg.h
lib/hnswlib/hnswlib/hnswlib.h
lib/hnswlib/hnswlib/space_ip.h
lib/hnswlib/hnswlib/space_l2.h
lib/hnswlib/hnswlib/visited_list_pool.h
lib/hnswlib/python_bindings/LazyIndex.py
lib/hnswlib/python_bindings/__init__.py
lib/hnswlib/python_bindings/bindings.cpp
lib/hnswlib/python_bindings/setup.py
lib/hnswlib/tests/cpp/download_bigann.py
lib/hnswlib/tests/cpp/main.cpp
lib/hnswlib/tests/cpp/multiThreadLoad_test.cpp
lib/hnswlib/tests/cpp/multiThread_replace_test.cpp
lib/hnswlib/tests/cpp/searchKnnCloserFirst_test.cpp
lib/hnswlib/tests/cpp/searchKnnWithFilter_test.cpp
lib/hnswlib/tests/cpp/sift_1b.cpp
lib/hnswlib/tests/cpp/sift_test.cpp
lib/hnswlib/tests/cpp/update_gen_data.py
lib/hnswlib/tests/cpp/updates_test.cpp
lib/hnswlib/tests/python/bindings_test.py
lib/hnswlib/tests/python/bindings_test_filter.py
lib/hnswlib/tests/python/bindings_test_getdata.py
lib/hnswlib/tests/python/bindings_test_labels.py
ncvis.egg-info/PKG-INFO
ncvis.egg-info/SOURCES.txt
ncvis.egg-info/dependency_links.txt
ncvis.egg-info/top_level.txt
