Metadata-Version: 2.1
Name: ncvis
Version: 1.5.10
Summary: Noise contrastive data visualization
Home-page: https://github.com/stat-ml/ncvis
Maintainer: Aleksandr Artemenkov
Maintainer-email: alartum@gmail.com
License: MIT
Project-URL: Source Code, https://github.com/stat-ml/ncvis
Classifier: Intended Audience :: Science/Research
Classifier: Intended Audience :: Developers
Classifier: License :: OSI Approved :: MIT License
Classifier: Programming Language :: C++
Classifier: Programming Language :: Python :: 3
Classifier: Operating System :: OS Independent
Requires-Python: >=3
License-File: LICENSE
